vishnuthinks/__init__.py
vishnuthinks/quiz.py
vishnuthinks-0.1.3.dist-info/LICENSE
vishnuthinks-0.1.3.dist-info/METADATA
vishnuthinks-0.1.3.dist-info/WHEEL
vishnuthinks-0.1.3.dist-info/entry_points.txt
vishnuthinks-0.1.3.dist-info/top_level.txt
vishnuthinks-0.1.3.dist-info/RECORD
